<!-- Pandora settings xml file -->

<pandora>
    <!-- GLOBAL SETTINGS -->
    <IsMonitoringEnabled>false</IsMonitoringEnabled>
    <ShouldDisplayAlgorithmInfo>false</ShouldDisplayAlgorithmInfo>
    <SingleHitTypeClusteringMode>true</SingleHitTypeClusteringMode>

    <!-- PLUGIN SETTINGS -->
    <MuonPlugin>LArMuonId</MuonPlugin>

    <!-- ALGORITHM SETTINGS -->
    <!--algorithm type = "EventReading">
         <EventFileName>/r05/lbne/mcproduction_v04_06_02/prodgenie_bnb_nu_cosmic_uboone/uBooNE_Events_100_0_reco1.pndr</EventFileName>
         <ShouldReadEvents>true</ShouldReadEvents>
         <SkipToEvent>0</SkipToEvent>
    </algorithm-->

    <!-- COSMIC RAY RECONSTRUCTION -->
    <algorithm type = "LArListPreparation">
        <OnlyAvailableCaloHits>true</OnlyAvailableCaloHits>
        <OutputCaloHitListNameW>CaloHitListW</OutputCaloHitListNameW>
        <OutputCaloHitListNameU>CaloHitListU</OutputCaloHitListNameU>
        <OutputCaloHitListNameV>CaloHitListV</OutputCaloHitListNameV>
        <FilteredCaloHitListName>CaloHitListFiltered</FilteredCaloHitListName>
        <CurrentCaloHitListReplacement>CaloHitListW</CurrentCaloHitListReplacement>
        <OutputMCParticleListNameU>MCParticleListU</OutputMCParticleListNameU>
        <OutputMCParticleListNameV>MCParticleListV</OutputMCParticleListNameV>
        <OutputMCParticleListNameW>MCParticleListW</OutputMCParticleListNameW>
        <OutputMCParticleListName3D>MCParticleList3D</OutputMCParticleListName3D>
        <CurrentMCParticleListReplacement>MCParticleList3D</CurrentMCParticleListReplacement>
        <MipEquivalentCut>0.</MipEquivalentCut>
    </algorithm>

    <algorithm type = "LArVisualMonitoring">
        <ShowMCParticles>false</ShowMCParticles>
        <ShowCurrentCaloHits>false</ShowCurrentCaloHits>
        <ShowCurrentTracks>false</ShowCurrentTracks>
        <ShowCurrentClusters>false</ShowCurrentClusters>
        <ShowCurrentPfos>false</ShowCurrentPfos>
        <CaloHitListNames>CaloHitListW CaloHitListU CaloHitListV</CaloHitListNames>
        <ShowDetector>false</ShowDetector>
        <BlackBackground>false</BlackBackground>
        <HitColors>iterate</HitColors>
        <DetectorView>xz</DetectorView>
    </algorithm>

    <!-- 2D cosmic ray reconstruction, W View -->
    <algorithm type = "LArClusteringParent">
        <algorithm type = "LArTrackClusterCreation" description = "ClusterFormation"/>
        <InputCaloHitListName>CaloHitListW</InputCaloHitListName>
        <ClusterListName>ClustersW</ClusterListName>
        <RestoreOriginalCaloHitList>false</RestoreOriginalCaloHitList>
    </algorithm>
    <algorithm type = "LArLayerSplitting"/>
    <algorithm type = "LArKinkSplitting"/>
    <algorithm type = "LArTransverseAssociation"/>
    <algorithm type = "LArLongitudinalAssociation"/>
    <algorithm type = "LArTransverseExtension"/>
    <algorithm type = "LArLongitudinalExtension"/>
    <algorithm type = "LArBranchSplitting"><CosmicMode>true</CosmicMode></algorithm>
    <algorithm type = "LArDeltaRaySplitting"><CosmicMode>true</CosmicMode></algorithm>
    <algorithm type = "LArCrossedTrackSplitting"/>
    <algorithm type = "LArCosmicRaySplitting"/>
    <algorithm type = "LArCosmicRayExtension"/>
    <algorithm type = "LArDeltaRayExtension"/>
    <algorithm type = "LArTrackConsolidation">
        <algorithm type = "LArSimpleClusterCreation" description = "ClusterRebuilding"/>
    </algorithm>

    <!-- 2D cosmic ray reconstruction, U View -->
    <algorithm type = "LArClusteringParent">
        <algorithm type = "LArTrackClusterCreation" description = "ClusterFormation"/>
        <InputCaloHitListName>CaloHitListU</InputCaloHitListName>
        <ClusterListName>ClustersU </ClusterListName>
        <RestoreOriginalCaloHitList>false</RestoreOriginalCaloHitList>
    </algorithm>
    <algorithm type = "LArLayerSplitting"/>
    <algorithm type = "LArKinkSplitting"/>
    <algorithm type = "LArTransverseAssociation"/>
    <algorithm type = "LArLongitudinalAssociation"/>
    <algorithm type = "LArTransverseExtension"/>
    <algorithm type = "LArLongitudinalExtension"/>
    <algorithm type = "LArBranchSplitting"><CosmicMode>true</CosmicMode></algorithm>
    <algorithm type = "LArDeltaRaySplitting"><CosmicMode>true</CosmicMode></algorithm>
    <algorithm type = "LArCrossedTrackSplitting"/>
    <algorithm type = "LArCosmicRaySplitting"/>
    <algorithm type = "LArCosmicRayExtension"/>
    <algorithm type = "LArDeltaRayExtension"/>
    <algorithm type = "LArTrackConsolidation">
        <algorithm type = "LArSimpleClusterCreation" description = "ClusterRebuilding"/>
    </algorithm>

    <!-- 2D cosmic ray reconstruction, V View -->
    <algorithm type = "LArClusteringParent">
        <algorithm type = "LArTrackClusterCreation" description = "ClusterFormation"/>
        <InputCaloHitListName>CaloHitListV</InputCaloHitListName>
        <ClusterListName>ClustersV</ClusterListName>
        <RestoreOriginalCaloHitList>false</RestoreOriginalCaloHitList>
    </algorithm>
    <algorithm type = "LArLayerSplitting"/>
    <algorithm type = "LArKinkSplitting"/>
    <algorithm type = "LArTransverseAssociation"/>
    <algorithm type = "LArLongitudinalAssociation"/>
    <algorithm type = "LArTransverseExtension"/>
    <algorithm type = "LArLongitudinalExtension"/>
    <algorithm type = "LArBranchSplitting"><CosmicMode>true</CosmicMode></algorithm>
    <algorithm type = "LArDeltaRaySplitting"><CosmicMode>true</CosmicMode></algorithm>
    <algorithm type = "LArCrossedTrackSplitting"/>
    <algorithm type = "LArCosmicRaySplitting"/>
    <algorithm type = "LArCosmicRayExtension"/>
    <algorithm type = "LArDeltaRayExtension"/>
    <algorithm type = "LArTrackConsolidation">
        <algorithm type = "LArSimpleClusterCreation" description = "ClusterRebuilding"/>
    </algorithm>

    <!-- 3D cosmic ray reconstruction -->
    <algorithm type = "LArThreeDTransverseTracks">
        <InputClusterListNameU>ClustersU</InputClusterListNameU>
        <InputClusterListNameV>ClustersV</InputClusterListNameV>
        <InputClusterListNameW>ClustersW</InputClusterListNameW>
        <OutputPfoListName>Particles3D</OutputPfoListName>
        <TrackTools>
            <tool type = "LArClearTracks"/>
            <tool type = "LArLongTracks"/>
            <tool type = "LArOvershootTracks"><SplitMode>true</SplitMode></tool>
            <tool type = "LArUndershootTracks"><SplitMode>true</SplitMode></tool>
            <tool type = "LArOvershootTracks"><SplitMode>false</SplitMode></tool>
            <tool type = "LArUndershootTracks"><SplitMode>false</SplitMode></tool>
            <tool type = "LArMissingTrackSegment"/>
            <tool type = "LArTrackSplitting"/>
            <tool type = "LArLongTracks"><MinMatchedFraction>0.75</MinMatchedFraction><MinXOverlapFraction>0.75</MinXOverlapFraction></tool>
            <tool type = "LArMissingTrack"/>
        </TrackTools>
    </algorithm>
    <algorithm type = "LArThreeDLongitudinalTracks">
        <InputClusterListNameU>ClustersU</InputClusterListNameU>
        <InputClusterListNameV>ClustersV</InputClusterListNameV>
        <InputClusterListNameW>ClustersW</InputClusterListNameW>
        <OutputPfoListName>Particles3D</OutputPfoListName>
        <TrackTools>
            <tool type = "LArClearLongitudinalTracks"/>
            <tool type = "LArMatchedEndPoints"/>
        </TrackTools>
    </algorithm>
    <algorithm type = "LArThreeDTrackFragments">
        <MinClusterLength>10.0</MinClusterLength>
        <InputClusterListNameU>ClustersU</InputClusterListNameU>
        <InputClusterListNameV>ClustersV</InputClusterListNameV>
        <InputClusterListNameW>ClustersW</InputClusterListNameW>
        <OutputPfoListName>Particles3D</OutputPfoListName>
        <TrackTools>
            <tool type = "LArClearTrackFragments"/>
        </TrackTools>
        <algorithm type = "LArSimpleClusterCreation" description = "ClusterRebuilding"/>
    </algorithm>
    <algorithm type = "LArCosmicRayTrackMatching">
        <InputClusterListNameU>ClustersU</InputClusterListNameU>
        <InputClusterListNameV>ClustersV</InputClusterListNameV>
        <InputClusterListNameW>ClustersW</InputClusterListNameW>
        <OutputPfoListName>Particles3D</OutputPfoListName>
    </algorithm>

    <!-- 2D cosmic ray shower clusters -->
    <algorithm type = "LArListDissolution">
        <WarnIfClustersUnavailable>false</WarnIfClustersUnavailable>
        <ClusterListNames>ClustersU ClustersV ClustersW</ClusterListNames>
    </algorithm>
    <algorithm type = "LArClusteringParent">
        <algorithm type = "LArSimpleClusterCreation" description = "ClusterFormation"/>
        <InputCaloHitListName>CaloHitListW</InputCaloHitListName>
        <ClusterListName>ClustersW</ClusterListName>
        <RestoreOriginalCaloHitList>false</RestoreOriginalCaloHitList>
    </algorithm>
    <algorithm type = "LArClusteringParent">
        <algorithm type = "LArSimpleClusterCreation" description = "ClusterFormation"/>
        <InputCaloHitListName>CaloHitListU</InputCaloHitListName>
        <ClusterListName>ClustersU</ClusterListName>
        <RestoreOriginalCaloHitList>false</RestoreOriginalCaloHitList>
    </algorithm>
    <algorithm type = "LArClusteringParent">
        <algorithm type = "LArSimpleClusterCreation" description = "ClusterFormation"/>
        <InputCaloHitListName>CaloHitListV</InputCaloHitListName>
        <ClusterListName>ClustersV</ClusterListName>
        <RestoreOriginalCaloHitList>false</RestoreOriginalCaloHitList>
    </algorithm>

    <!-- 2D/3D cosmic ray shower reconstruction -->
    <algorithm type = "LArDeltaRayIdentification">
        <ParentPfoListName>Particles3D</ParentPfoListName>
        <DaughterPfoListName>DaughterParticles3D</DaughterPfoListName>
    </algorithm>
    <algorithm type = "LArDeltaRayGrowing">
        <InputClusterListName>ClustersW</InputClusterListName>
        <ParentPfoListName>Particles3D</ParentPfoListName>
        <DaughterPfoListName>DaughterParticles3D</DaughterPfoListName>
    </algorithm>
    <algorithm type = "LArDeltaRayGrowing">
        <InputClusterListName>ClustersU</InputClusterListName>
        <ParentPfoListName>Particles3D</ParentPfoListName>
        <DaughterPfoListName>DaughterParticles3D</DaughterPfoListName>
    </algorithm>
    <algorithm type = "LArDeltaRayGrowing">
        <InputClusterListName>ClustersV</InputClusterListName>
        <ParentPfoListName>Particles3D</ParentPfoListName>
        <DaughterPfoListName>DaughterParticles3D</DaughterPfoListName>
    </algorithm>
    <algorithm type = "LArDeltaRayMatching">
        <ParentPfoListName>Particles3D</ParentPfoListName>
        <DaughterPfoListName>DaughterParticles3D</DaughterPfoListName>
        <InputClusterListNameU>ClustersU</InputClusterListNameU>
        <InputClusterListNameV>ClustersV</InputClusterListNameV>
        <InputClusterListNameW>ClustersW</InputClusterListNameW>
    </algorithm>

    <!-- 2D/3D cosmic ray shower remnants -->  
    <algorithm type = "LArSimpleClusterGrowing">
        <InputClusterListName>ClustersW</InputClusterListName>
        <MinCaloHitsPerCluster>5</MinCaloHitsPerCluster>
    </algorithm>
    <algorithm type = "LArSimpleClusterGrowing">
        <InputClusterListName>ClustersU</InputClusterListName>
        <MinCaloHitsPerCluster>5</MinCaloHitsPerCluster>
    </algorithm>
    <algorithm type = "LArSimpleClusterGrowing">
        <InputClusterListName>ClustersV</InputClusterListName>
        <MinCaloHitsPerCluster>5</MinCaloHitsPerCluster>
    </algorithm>
    <algorithm type = "LArSimpleClusterMerging">
        <InputClusterListName>ClustersW</InputClusterListName>
        <MinCaloHitsPerCluster>5</MinCaloHitsPerCluster>
    </algorithm>
    <algorithm type = "LArSimpleClusterMerging">
        <InputClusterListName>ClustersU</InputClusterListName>
        <MinCaloHitsPerCluster>5</MinCaloHitsPerCluster>
    </algorithm>
    <algorithm type = "LArSimpleClusterMerging">
        <InputClusterListName>ClustersV</InputClusterListName>
        <MinCaloHitsPerCluster>5</MinCaloHitsPerCluster>
    </algorithm>
    <algorithm type = "LArThreeDRemnants">
        <MinClusterCaloHits>5</MinClusterCaloHits>
        <InputClusterListNameU>ClustersU</InputClusterListNameU>
        <InputClusterListNameV>ClustersV</InputClusterListNameV>
        <InputClusterListNameW>ClustersW</InputClusterListNameW>
        <OutputPfoListName>Particles3D</OutputPfoListName>
        <TrackTools>
            <tool type = "LArClearRemnants"/>
            <tool type = "LArConnectedRemnants"/>
        </TrackTools>
    </algorithm>
    <algorithm type = "LArThreeDRemnants">
        <MinClusterCaloHits>2</MinClusterCaloHits>
        <InputClusterListNameU>ClustersU</InputClusterListNameU>
        <InputClusterListNameV>ClustersV</InputClusterListNameV>
        <InputClusterListNameW>ClustersW</InputClusterListNameW>
        <OutputPfoListName>Particles3D</OutputPfoListName>
        <TrackTools>
            <tool type = "LArClearRemnants"/>
            <tool type = "LArConnectedRemnants"/>
            <tool type = "LArMopUpRemnants"/>
        </TrackTools>
    </algorithm>
    <algorithm type = "LArCosmicRayShowerMatching">
        <MinCaloHitsPerCluster>1</MinCaloHitsPerCluster>
        <InputClusterListNameU>ClustersU</InputClusterListNameU>
        <InputClusterListNameV>ClustersV</InputClusterListNameV>
        <InputClusterListNameW>ClustersW</InputClusterListNameW>
        <OutputPfoListName>Particles3D</OutputPfoListName>
    </algorithm>

    <!-- 2D cosmic-ray isolated hits -->  
    <algorithm type = "LArIsolatedHitMerging">
        <PfoListNames>Particles3D DaughterParticles3D</PfoListNames>
        <RemnantClusterListNames>ClustersU ClustersV ClustersW</RemnantClusterListNames>
        <ExcludePfosContainingTracks>false</ExcludePfosContainingTracks>
    </algorithm>

    <!-- 3D cosmic-ray hit creation -->
    <algorithm type = "LArThreeDHitCreation">
        <InputPfoListName>Particles3D</InputPfoListName>
        <OutputCaloHitListName>CaloHitList3D</OutputCaloHitListName>
        <OutputClusterListName>Clusters3D</OutputClusterListName>
        <HitCreationTools>
            <tool type = "LArClearTransverseTrackHits"><MinViews>3</MinViews></tool>
            <tool type = "LArClearLongitudinalTrackHits"><MinViews>3</MinViews></tool>
            <tool type = "LArMultiValuedLongitudinalTrackHits"><MinViews>3</MinViews></tool>
            <tool type = "LArMultiValuedTransverseTrackHits"><MinViews>3</MinViews></tool>
            <tool type = "LArClearTransverseTrackHits"><MinViews>2</MinViews></tool>
            <tool type = "LArClearLongitudinalTrackHits"><MinViews>2</MinViews></tool>
            <tool type = "LArMultiValuedLongitudinalTrackHits"><MinViews>2</MinViews></tool>
        </HitCreationTools>
    </algorithm>
    <algorithm type = "LArThreeDHitCreation">
        <InputPfoListName>Particles3D</InputPfoListName>
        <OutputCaloHitListName>CaloHitList3D</OutputCaloHitListName>
        <OutputClusterListName>Clusters3D</OutputClusterListName>
        <HitCreationTools>
            <tool type = "LArThreeViewShowerHits">
                <ChiSquaredCut>5.0</ChiSquaredCut>
                <ZTolerance>3.0</ZTolerance>
            </tool>
            <tool type = "LArTwoViewShowerHits">
                <ChiSquaredCut>5.0</ChiSquaredCut>
                <XTolerance>2.0</XTolerance> 
            </tool>
        </HitCreationTools>
    </algorithm>
    <algorithm type = "LArThreeDHitCreation">
        <InputPfoListName>DaughterParticles3D</InputPfoListName>
        <OutputCaloHitListName>DaughterCaloHitList3D</OutputCaloHitListName>
        <OutputClusterListName>DaughterClusters3D</OutputClusterListName>
        <HitCreationTools>
            <tool type = "LArThreeViewShowerHits">
                <ChiSquaredCut>5.0</ChiSquaredCut>
                <ZTolerance>3.0</ZTolerance>
            </tool>
            <tool type = "LArTwoViewShowerHits">
                <ChiSquaredCut>5.0</ChiSquaredCut>
                <XTolerance>2.0</XTolerance> 
            </tool>
            <tool type = "LArDeltaRayShowerHits">
            </tool>
        </HitCreationTools>
    </algorithm>

    <!-- 3D cosmic-ray vertex reconstruction -->
    <algorithm type = "LArCosmicRayVertexBuilding">
        <InputPfoListName>Particles3D</InputPfoListName>
        <OutputVertexListName>Vertices3D</OutputVertexListName>
    </algorithm>

    <!-- 3D cosmic-ray track and shower reconstruction -->
    <algorithm type = "LArTrackParticleBuilding">
        <CosmicMode>true</CosmicMode>
        <PfoListName>Particles3D</PfoListName>
        <VertexListName>Vertices3D</VertexListName>
    </algorithm>

    <algorithm type = "LArShowerParticleBuilding">
        <CosmicMode>true</CosmicMode>
        <PfoListName>DaughterParticles3D</PfoListName>
        <VertexListName>Vertices3D</VertexListName>
    </algorithm>

    <!-- FINAL PARTICLE OUTPUT -->
    <algorithm type = "LArListChanging">
        <PfoListName>Particles3D</PfoListName>
    </algorithm>

    <algorithm type = "LArVisualMonitoring">
        <ShowMCParticles>false</ShowMCParticles>
        <ShowCurrentCaloHits>false</ShowCurrentCaloHits>
        <ShowCurrentTracks>false</ShowCurrentTracks>
        <ShowCurrentClusters>false</ShowCurrentClusters>
        <ShowCurrentPfos>false</ShowCurrentPfos>
        <PfoListNames>Particles3D</PfoListNames>
        <ShowDetector>false</ShowDetector>
        <ShowOnlyAvailable>false</ShowOnlyAvailable>
        <BlackBackground>false</BlackBackground>
        <HitColors>iterate</HitColors>
        <DetectorView>xz</DetectorView>
    </algorithm>

    <algorithm type = "LArVisualMonitoring">
        <ShowMCParticles>false</ShowMCParticles>
        <ShowCurrentCaloHits>false</ShowCurrentCaloHits>
        <ShowCurrentTracks>false</ShowCurrentTracks>
        <ShowCurrentClusters>false</ShowCurrentClusters>
        <ShowCurrentPfos>false</ShowCurrentPfos>
        <ClusterListNames>Clusters3D DaughterClusters3D</ClusterListNames>
        <ShowDetector>false</ShowDetector>
        <ShowOnlyAvailable>false</ShowOnlyAvailable>
        <BlackBackground>false</BlackBackground>
        <HitColors>iterate</HitColors>
        <DetectorView>xz</DetectorView>
    </algorithm>

    <algorithm type = "LArVisualMonitoring">
        <ShowMCParticles>false</ShowMCParticles>
        <ShowCurrentCaloHits>false</ShowCurrentCaloHits>
        <ShowCurrentTracks>false</ShowCurrentTracks>
        <ShowCurrentClusters>false</ShowCurrentClusters>
        <ShowCurrentPfos>false</ShowCurrentPfos>
        <ClusterListNames>ClustersU ClustersV ClustersW</ClusterListNames>
        <CaloHitListNames>CaloHitListU CaloHitListV CaloHitListW</CaloHitListNames>
        <ShowDetector>false</ShowDetector>
        <ShowOnlyAvailable>true</ShowOnlyAvailable>
        <BlackBackground>false</BlackBackground>
        <HitColors>iterate</HitColors>
        <DetectorView>xz</DetectorView>
    </algorithm>
</pandora>
